{
    "items": [
        {
            "playerName": "walter white",
            "points": 2
        },
        {
            "playerName": "jessie pinkman",
            "points": 2
        },
        {
            "playerName": "pawel k",
            "points": 2
        },
        {
            "playerName": "janusz",
            "points": 2
        },
        {
            "playerName": "asds",
            "points": 2
        },
        {
            "playerName": "pawelk",
            "points": 2
        },
        {
            "playerName": "kkkkk",
            "points": 2
        }
    ]
}